madnet/__init__.py
madnet/nn.py
madnet/tensor.py
madnet-0.0.1.dist-info/LICENSE
madnet-0.0.1.dist-info/METADATA
madnet-0.0.1.dist-info/WHEEL
madnet-0.0.1.dist-info/top_level.txt
madnet-0.0.1.dist-info/RECORD
