Metadata-Version: 2.1
Name: madnet
Version: 0.0.1
Summary: Tensor-based autdiff engine and neural network API
Author: Jordan Madden
Author-email: <jordanmadden285@gmail.com>
Keywords: python,tensors,neural networks,automatic differentiation
Classifier: Development Status :: 1 - Planning
Classifier: Intended Audience :: Developers
Classifier: Programming Language :: Python :: 3
Classifier: Operating System :: Unix
Classifier: Operating System :: MacOS :: MacOS X
Classifier: Operating System :: Microsoft :: Windows
License-File: LICENSE
Requires-Dist: numpy
